PyWinda/OM_module.py
PyWinda/__init__.py
PyWinda/dfm_module.py
PyWinda/pwploter.py
PyWinda/pywinda.py
tests/__init__.py
tests/test_OM_module.py
tests/test_dfm_module.py
tests/test_pywinda.py
PyWinda-1.2.12.dist-info/LICENSE
PyWinda-1.2.12.dist-info/METADATA
PyWinda-1.2.12.dist-info/WHEEL
PyWinda-1.2.12.dist-info/top_level.txt
PyWinda-1.2.12.dist-info/RECORD
