Metadata-Version: 2.1
Name: PyWinda
Version: 1.2.12
Summary: PyWinda provides an extensive range of tools for power and load analysis at a wind farm level.
Home-page: https://github.com/PyWinda/pywinda
Author: PyWinda Authors
Author-email: 
License: BSD-3-Clause
Project-URL: Bug Tracker, https://github.com/PyWinda/pywinda/issues
Platform: UNKNOWN
Classifier: Programming Language :: Python :: 3
Classifier: License :: OSI Approved :: BSD License
Classifier: Operating System :: OS Independent
Requires-Dist: pandas
Requires-Dist: numpy
Requires-Dist: matplotlib
